HammingEncoder/HammingEncoder.py
HammingEncoder/__init__.py
HammingEncoder/data_generator.py
HammingEncoder/test.py
HammingEncoder/train_function.py
HammingEncoder-0.1.8.dist-info/METADATA
HammingEncoder-0.1.8.dist-info/WHEEL
HammingEncoder-0.1.8.dist-info/top_level.txt
HammingEncoder-0.1.8.dist-info/RECORD
